[{"id":"MX-AGU","value":645.0},{"id":"MX-BCN","value":8315.0},{"id":"MX-BCS","value":2099.0},{"id":"MX-CAM","value":43.0},{"id":"MX-CHP","value":1964.0},{"id":"MX-CHH","value":11960.0},{"id":"MX-CMX","value":18426.0},{"id":"MX-COA","value":6885.0},{"id":"MX-COL","value":582.0},{"id":"MX-DUR","value":5272.0},{"id":"MX-GUA","value":11133.0},{"id":"MX-GRO","value":2183.0},{"id":"MX-HID","value":3078.0},{"id":"MX-JAL","value":11431.0},{"id":"MX-MIC","value":787.0},{"id":"MX-MOR","value":4516.0},{"id":"MX-MEX","value":5474.0},{"id":"MX-NAY","value":476.0},{"id":"MX-NLE","value":17773.0},{"id":"MX-OAX","value":3353.0},{"id":"MX-PUE","value":5586.0},{"id":"MX-QUE","value":965.0},{"id":"MX-ROO","value":1524.0},{"id":"MX-SLP","value":3930.0},{"id":"MX-SIN","value":2371.0},{"id":"MX-SON","value":3595.0},{"id":"MX-TAB","value":5406.0},{"id":"MX-TAM","value":6378.0},{"id":"MX-TLA","value":6.0},{"id":"MX-VER","value":4771.0},{"id":"MX-YUC","value":2270.0},{"id":"MX-ZAC","value":1075.0}]