[{"id":"MX-AGU","value":0.0},{"id":"MX-BCN","value":1909.0},{"id":"MX-BCS","value":429.0},{"id":"MX-CAM","value":341.0},{"id":"MX-CHP","value":169.0},{"id":"MX-CHH","value":2044.0},{"id":"MX-CMX","value":4742.0},{"id":"MX-COA","value":935.0},{"id":"MX-COL","value":402.0},{"id":"MX-DUR","value":546.0},{"id":"MX-GUA","value":1491.0},{"id":"MX-GRO","value":431.0},{"id":"MX-HID","value":756.0},{"id":"MX-JAL","value":5002.0},{"id":"MX-MIC","value":631.0},{"id":"MX-MOR","value":622.0},{"id":"MX-MEX","value":5313.0},{"id":"MX-NAY","value":277.0},{"id":"MX-NLE","value":1812.0},{"id":"MX-OAX","value":587.0},{"id":"MX-PUE","value":915.0},{"id":"MX-QUE","value":745.0},{"id":"MX-ROO","value":1085.0},{"id":"MX-SLP","value":723.0},{"id":"MX-SIN","value":554.0},{"id":"MX-SON","value":796.0},{"id":"MX-TAB","value":250.0},{"id":"MX-TAM","value":863.0},{"id":"MX-TLA","value":13.0},{"id":"MX-VER","value":1116.0},{"id":"MX-YUC","value":103.0},{"id":"MX-ZAC","value":314.0}]