[{"id":"MX-AGU","value":3543.0},{"id":"MX-BCN","value":4684.0},{"id":"MX-BCS","value":1504.0},{"id":"MX-CAM","value":516.0},{"id":"MX-CHP","value":512.0},{"id":"MX-CHH","value":3747.0},{"id":"MX-CMX","value":16819.0},{"id":"MX-COA","value":5403.0},{"id":"MX-COL","value":2749.0},{"id":"MX-DUR","value":1274.0},{"id":"MX-GUA","value":9912.0},{"id":"MX-GRO","value":2184.0},{"id":"MX-HID","value":2301.0},{"id":"MX-JAL","value":10250.0},{"id":"MX-MIC","value":4498.0},{"id":"MX-MOR","value":4647.0},{"id":"MX-MEX","value":0.0},{"id":"MX-NAY","value":96.0},{"id":"MX-NLE","value":5954.0},{"id":"MX-OAX","value":4377.0},{"id":"MX-PUE","value":5784.0},{"id":"MX-QUE","value":3993.0},{"id":"MX-ROO","value":2664.0},{"id":"MX-SLP","value":2834.0},{"id":"MX-SIN","value":1311.0},{"id":"MX-SON","value":1368.0},{"id":"MX-TAB","value":4834.0},{"id":"MX-TAM","value":1808.0},{"id":"MX-TLA","value":25.0},{"id":"MX-VER","value":7137.0},{"id":"MX-YUC","value":1898.0},{"id":"MX-ZAC","value":1265.0}]